Metadata-Version: 1.0
Name: ovnlp
Version: 0.0.4
Summary: Openvalue toolkit to use word vectors
Home-page: https://github.com/Fanchouille/ovnlp
Author: Francois Valadier
Author-email: francois.valadier@gmail.com
License: MIT
Platform: UNKNOWN
